<?xml version="1.0" encoding="utf-8" ?>
<odoo>
    <data>
        <record id="product_template_form_view" model="ir.ui.view">
            <field name="name">product.template.common.form</field>
            <field name="model">product.template</field>
            <field name="inherit_id" ref="product.product_template_form_view" />
            <field name="priority" eval="50" />
            <field name="arch" type="xml">
                <page name="purchase" position="inside">
                    <group name="purchase_price_history">
                        <field name="min_purchase_price" />
                        <field name="max_purchase_price" />
                        <field name="avg_purchase_price" />
                    </group>
                </page>
            </field>
        </record>
    </data>
</odoo>
